{
  "prompts": {
    "name": {
      "type": "string",
      "required": true,
      "label": "Project name, single word, no space or punctuations"
    },
    "description": {
      "type": "string",
      "required": true,
      "label": "Project description",
      "default": "A Vue.js project"
    },
    "author": {
      "type": "string",
      "label": "Author"
    },
    "license": {
      "type": "string",
      "label": "License",
      "default": "MIT"
    },
    "host": {
      "type": "string",
      "required": true,
      "label": "Web site host name, like 'google'"
    },
    "port": {
      "type": "number",
      "required": true,
      "default": 8080,
      "label": "dev server port"
    }
  },
  "completeMessage": "{{#inPlace}}To get started:\n\n  npm install\n  npm run dev{{else}}To get started:\n\n  cd {{destDirName}}\n  npm install\n  npm run dev{{/inPlace}}"
}